mortgage_filter/__init__.py
mortgage_filter/exceptions.py
mortgage_filter/mortgage_base.py
mortgage_filter/mortgage_filter.py
mortgage_pkg-1.0.1.dist-info/licenses/LICENSE.md
mortgage_pkg-1.0.1.dist-info/METADATA
mortgage_pkg-1.0.1.dist-info/WHEEL
mortgage_pkg-1.0.1.dist-info/top_level.txt
mortgage_pkg-1.0.1.dist-info/RECORD
